fastapi_task_manager/__init__.py
fastapi_task_manager/config.py
fastapi_task_manager/force_acquire_semaphore.py
fastapi_task_manager/py.typed
fastapi_task_manager/runner.py
fastapi_task_manager/schema/__init__.py
fastapi_task_manager/schema/task.py
fastapi_task_manager/schema/task_group.py
fastapi_task_manager/task_group.py
fastapi_task_manager/task_manager.py
fastapi_task_manager/task_router_services.py
fastapi_task_manager-0.7.0.dist-info/WHEEL
fastapi_task_manager-0.7.0.dist-info/METADATA
fastapi_task_manager-0.7.0.dist-info/RECORD
