Metadata-Version: 2.3
Name: fastapi-task-manager
Version: 0.7.0
Summary: A task manager for Fastapi. Robust Scheduling, Distributed Safety
Keywords: fastapi,task-manager,task-scheduler,distributed,safety,robust
Author: Matteo Morando
Author-email: Matteo Morando <matteo.morando98@gmail.com>
License: MIT License
Classifier: Development Status :: 3 - Alpha
Classifier: Intended Audience :: Developers
Classifier: License :: OSI Approved :: MIT License
Classifier: Programming Language :: Python :: 3
Classifier: Programming Language :: Python :: 3.10
Classifier: Programming Language :: Python :: 3.11
Classifier: Programming Language :: Python :: 3.12
Classifier: Programming Language :: Python :: 3.13
Classifier: Programming Language :: Python :: 3.14
Classifier: Framework :: FastAPI
Classifier: Operating System :: OS Independent
Requires-Dist: cronexpr>=0.30.0
Requires-Dist: fastapi>=0.115.13
Requires-Dist: pydantic>=2.11.7
Requires-Dist: redis>=6.2.0
Requires-Python: >=3.10
Project-URL: Bug Tracker, https://github.com/Morry98/fastapi-task-manager/repo/issues
Project-URL: Homepage, https://github.com/Morry98/fastapi-task-manager
